botnodes/__init__.py
botnodes/nodes.py
botnodes/union_serialize.py
botnodes-0.1.0.dist-info/licenses/LICENSE
botnodes-0.1.0.dist-info/METADATA
botnodes-0.1.0.dist-info/WHEEL
botnodes-0.1.0.dist-info/top_level.txt
botnodes-0.1.0.dist-info/RECORD
