Metadata-Version: 2.4
Name: botnodes
Version: 0.1.0
Summary: Async user state for bots (with Redis)
Author-email: Aleksei Chebotarev <me@nikuda.org>
License-Expression: MIT
Project-URL: Homepage, https://github.com/nikudaorg/botnodes
Requires-Python: >=3.11
License-File: LICENSE
Dynamic: license-file
